lcdp_deployment_manager/__init__.py
lcdp_deployment_manager/common.py
lcdp_deployment_manager/constant.py
lcdp_deployment_manager/deployment_executor.py
lcdp_deployment_manager/deployment_manager.py
lcdp_deployment_manager/deployment_manager_factory.py
lcdp_deployment_manager/manage_alb.py
lcdp_deployment_manager/manage_ecr.py
lcdp_deployment_manager/manage_ecs.py
lcdp_deployment_manager/manage_ses.py
lcdp_test-1.0.17.dist-info/LICENSE
lcdp_test-1.0.17.dist-info/METADATA
lcdp_test-1.0.17.dist-info/WHEEL
lcdp_test-1.0.17.dist-info/top_level.txt
lcdp_test-1.0.17.dist-info/RECORD
